RabbitMq.py
robotframework_rabbitmq-3.0.0.dist-info/LICENSE
robotframework_rabbitmq-3.0.0.dist-info/METADATA
robotframework_rabbitmq-3.0.0.dist-info/WHEEL
robotframework_rabbitmq-3.0.0.dist-info/top_level.txt
robotframework_rabbitmq-3.0.0.dist-info/RECORD
