Metadata-Version: 2.1
Name: robotframework-rabbitmq
Version: 3.0.0
Summary: A Robot Framework RabbitMq Library
Home-page: https://github.com/peterservice-rnd/robotframework-rabbitmq
Author: JSC PETER-SERVICE
Author-email: drse_aist_all@billing.ru
License: Apache License 2.0
Keywords: testing testautomation robotframework rabbitmq amqp
Platform: UNKNOWN
Classifier: Development Status :: 5 - Production/Stable
Classifier: Intended Audience :: Developers
Classifier: Topic :: Software Development :: Testing
Classifier: License :: OSI Approved :: Apache Software License
Classifier: Programming Language :: Python :: 3.5
Classifier: Programming Language :: Python :: 3.6
Classifier: Framework :: Robot Framework :: Library
Requires-Dist: pika (==0.12.0)
Requires-Dist: requests (>=2.20.0)
Requires-Dist: robotframework (==3.0.4)
